kfp_decorators/__init__.py
kfp_decorators/_version.py
kfp_decorators-0.0.1.dist-info/METADATA
kfp_decorators-0.0.1.dist-info/WHEEL
kfp_decorators-0.0.1.dist-info/licenses/LICENSE
kfp_decorators-0.0.1.dist-info/RECORD
